fabsec/__init__.py
fabsec/client.py
fabsec/errors.py
fabsec/types.py
fabsec-0.1.3.dist-info/METADATA
fabsec-0.1.3.dist-info/WHEEL
fabsec-0.1.3.dist-info/top_level.txt
fabsec-0.1.3.dist-info/RECORD
