Metadata-Version: 2.4
Name: fabsec
Version: 0.1.3
Summary: FabSec SDK – Security & AI Platform
Author-email: Sudofab <sudomata@gmail.com>
Project-URL: Homepage, https://pypi.org/project/fabsec/
Project-URL: Repository, https://github.com/sudomata/fabsec-python-sdk
Project-URL: Issues, https://github.com/sudomata/fabsec-python-sdk/issues
Keywords: security,sdk,api,ai
Classifier: Programming Language :: Python :: 3
Classifier: Programming Language :: Python :: 3 :: Only
Classifier: License :: OSI Approved :: MIT License
Classifier: Operating System :: OS Independent
Requires-Python: >=3.9
Requires-Dist: requests>=2.31.0
